CryptoPayAPI/__init__.py
CryptoPayAPI/api.py
CryptoPayAPI/errors.py
CryptoPayAPI/schemas.py
CryptoPayAPI/types.py
pycryptopay_sdk-1.7.1.dist-info/METADATA
pycryptopay_sdk-1.7.1.dist-info/LICENSE
pycryptopay_sdk-1.7.1.dist-info/WHEEL
pycryptopay_sdk-1.7.1.dist-info/RECORD
