Metadata-Version: 2.1
Name: pycryptopay-sdk
Version: 1.7.1
Summary: Python API wrapper for CryptoPay API
Home-page: https://github.com/LulzLoL231/pyCryptoPayAPI/
License: MIT
Keywords: cryptopay,crypto
Author: Maxim Mosin
Author-email: max@mosin.pw
Requires-Python: >=3.8.1,<4.0.0
Classifier: Development Status :: 5 - Production/Stable
Classifier: Framework :: AsyncIO
Classifier: License :: OSI Approved :: MIT License
Classifier: Operating System :: OS Independent
Classifier: Programming Language :: Python :: 3
Classifier: Programming Language :: Python :: 3.9
Classifier: Programming Language :: Python :: 3.10
Classifier: Programming Language :: Python :: 3.11
Classifier: Topic :: Software Development :: Libraries :: Python Modules
Requires-Dist: httpx (>=0.23.1,<0.24.0)
Requires-Dist: pydantic (>=1.10.2,<2.0.0)
Project-URL: Documentation, https://lulzlol231.github.io/pyCryptoPayAPI
Project-URL: Repository, https://github.com/LulzLoL231/pyCryptoPayAPI
